WHOISGUNA/__init__.py
whoisguna-0.0.1.dist-info/LICENSE.txt
whoisguna-0.0.1.dist-info/METADATA
whoisguna-0.0.1.dist-info/WHEEL
whoisguna-0.0.1.dist-info/top_level.txt
whoisguna-0.0.1.dist-info/RECORD
