Metadata-Version: 2.1
Name: whoisguna
Version: 0.0.1
Summary: Details about guna
Home-page: UNKNOWN
Author: Avadi Guna
Author-email: guna0professional@gmail.com
License: UNKNOWN
Platform: UNKNOWN
Classifier: Development Status :: 5 - Production/Stable
Classifier: Intended Audience :: Education
Classifier: Operating System :: OS Independent
Classifier: License :: OSI Approved :: MIT License
Classifier: Programming Language :: Python :: 3
License-File: LICENSE.txt
